CHANGELOG.md
LICENSE
MANIFEST.in
README.md
VERSION
setup.cfg
setup.py
arcutils/__init__.py
arcutils/__main__.py
arcutils/admin.py
arcutils/colorize.py
arcutils/const.py
arcutils/context_processors.py
arcutils/decorators.py
arcutils/exc.py
arcutils/forms.py
arcutils/local.base.cfg
arcutils/middleware.py
arcutils/path.py
arcutils/registry.py
arcutils/response.py
arcutils/settings.py
arcutils/staticfiles.py
arcutils/tasks.py
arcutils/threadlocals.py
arcutils/views.py
arcutils/wsgi.py
arcutils/auditor/__init__.py
arcutils/auditor/apps.py
arcutils/auditor/middleware.py
arcutils/auditor/models.py
arcutils/auditor/settings.py
arcutils/auditor/signals.py
arcutils/auditor/utils.py
arcutils/auditor/migrations/0001_initial.py
arcutils/auditor/migrations/0002_order_audit_log_records_by_most_recent_first.py
arcutils/auditor/migrations/__init__.py
arcutils/cas/__init__.py
arcutils/cas/backends.py
arcutils/cas/callbacks.py
arcutils/cas/settings.py
arcutils/cas/urls.py
arcutils/cas/utils.py
arcutils/cas/views.py
arcutils/db/__init__.py
arcutils/db/models/__init__.py
arcutils/db/models/audit.py
arcutils/drf/__init__.py
arcutils/drf/authentication.py
arcutils/drf/renderers.py
arcutils/drf/routers.py
arcutils/drf/serializers.py
arcutils/ldap/__init__.py
arcutils/ldap/connection.py
arcutils/ldap/profile.py
arcutils/ldap/search.py
arcutils/ldap/settings.py
arcutils/ldap/utils.py
arcutils/management/__init__.py
arcutils/management/commands/__init__.py
arcutils/management/commands/collectstatic.py
arcutils/management/commands/findunusedtemplates.py
arcutils/management/commands/showsettings.py
arcutils/masquerade/__init__.py
arcutils/masquerade/middleware.py
arcutils/masquerade/perms.py
arcutils/masquerade/settings.py
arcutils/masquerade/urls.py
arcutils/masquerade/util.py
arcutils/masquerade/views.py
arcutils/masquerade/templatetags/__init__.py
arcutils/masquerade/templatetags/masquerade.py
arcutils/static/favicon.ico
arcutils/static/robots.txt
arcutils/templates/foundation.html
django_arcutils.egg-info/PKG-INFO
django_arcutils.egg-info/SOURCES.txt
django_arcutils.egg-info/dependency_links.txt
django_arcutils.egg-info/entry_points.txt
django_arcutils.egg-info/not-zip-safe
django_arcutils.egg-info/requires.txt
django_arcutils.egg-info/top_level.txt