Metadata-Version: 1.1
Name: django-arcutils
Version: 2.24.0
Summary: Common utilities used in WDT Django projects
Home-page: https://github.com/PSU-OIT-ARC/django-arcutils
Author: PSU - OIT - WDT
Author-email: webteam@pdx.edu
License: UNKNOWN
Platform: UNKNOWN
Classifier: Development Status :: 4 - Beta
Classifier: Framework :: Django
Classifier: Programming Language :: Python :: 3
Classifier: Programming Language :: Python :: 3.3
Classifier: Programming Language :: Python :: 3.4
Classifier: Programming Language :: Python :: 3.5
Classifier: Programming Language :: Python :: 3.6
